iban_validation_polars-0.1.26.dist-info/METADATA
iban_validation_polars-0.1.26.dist-info/WHEEL
iban_validation_polars/__init__.py
iban_validation_polars/__pycache__/__init__.cpython-39.pyc
iban_validation_polars/__pycache__/__init__.cpython-312.pyc
iban_validation_polars/iban_validation_polars.cpython-312-aarch64-linux-gnu.so
iban_validation_polars-0.1.26.dist-info/RECORD
