Metadata-Version: 2.3
Name: iban_validation_polars
Version: 0.1.26
Classifier: Programming Language :: Python :: 3
Classifier: License :: OSI Approved :: MIT License
Summary: A package to facilitate validation of IBANs and selecting Bank identifier and Branch identifier as a Polars plugin
Author: Eric
License: MIT
Requires-Python: >=3.9
Project-URL: Homepage, https://github.com/ericqu/iban_validation/tree/main/iban_validation_polars
Project-URL: Issues, https://github.com/ericqu/iban_validation/issues
